README.md
setup.py
Lab3py_farisey.egg-info/PKG-INFO
Lab3py_farisey.egg-info/SOURCES.txt
Lab3py_farisey.egg-info/dependency_links.txt
Lab3py_farisey.egg-info/top_level.txt
serializer/src/__init__.py
serializer/src/constants.py
serializer/src/converter.py
serializer/src/factory.py
serializer/src/json_serializer.py
serializer/src/supportive.py
serializer/src/xml_serializer.py