Metadata-Version: 2.1
Name: Lab3py-farisey
Version: 0.1.0
Summary: serialization
Home-page: UNKNOWN
Author: yury farisey
Author-email: fariseyd@mail.ru
License: UNKNOWN
Platform: UNKNOWN
Classifier: Intended Audience :: Developers
Classifier: Programming Language :: Python :: 3.10
Classifier: Operating System :: OS Independent
